timerangeparser/__init__.py
timerangeparser-0.0.5.dist-info/METADATA
timerangeparser-0.0.5.dist-info/WHEEL
timerangeparser-0.0.5.dist-info/top_level.txt
timerangeparser-0.0.5.dist-info/RECORD
